cadasta/__init__.py
cadasta/workertoolbox/__init__.py
cadasta/workertoolbox/conf.py
cadasta/workertoolbox/setup.py
cadasta/workertoolbox/signals.py
cadasta/workertoolbox/tests.py
cadasta/workertoolbox/utils.py
cadasta_workertoolbox-0.6.0.dist-info/DESCRIPTION.rst
cadasta_workertoolbox-0.6.0.dist-info/METADATA
cadasta_workertoolbox-0.6.0.dist-info/RECORD
cadasta_workertoolbox-0.6.0.dist-info/WHEEL
cadasta_workertoolbox-0.6.0.dist-info/metadata.json
cadasta_workertoolbox-0.6.0.dist-info/top_level.txt
tests/__init__.py
tests/test_conf.py
tests/test_functional.py
tests/test_setup.py
tests/test_utils.py
