Metadata-Version: 2.0
Name: cadasta-workertoolbox
Version: 0.6.0
Summary: Cadasta Worker Toolbox
Home-page: https://github.com/Cadasta/cadasta-workertoolbox
Author: Anthony Lukach
Author-email: alukach@cadasta.org
License: GNU Affero General Public License v3.0
Platform: UNKNOWN
Classifier: Development Status :: 3 - Alpha
Requires-Dist: SQLAlchemy (>=1.2,<1.3)
Requires-Dist: boto3 (<1.7,>=1.6)
Requires-Dist: celery (>=4.1.0,<=4.2)
Requires-Dist: kombu (>=4.1.0,<=4.2)
Requires-Dist: mock (>=2.0.0)
Requires-Dist: psycopg2 (>=2.7.1)
Requires-Dist: pycurl (>=7.43.0,<=7.44)
Requires-Dist: raven (>=6.6.0)
